msp360/__init__.py
msp360/client.py
msp360/exceptions.py
msp360/models.py
msp360/py.typed
msp360-0.0.1.dev1.dist-info/LICENSE
msp360-0.0.1.dev1.dist-info/METADATA
msp360-0.0.1.dev1.dist-info/WHEEL
msp360-0.0.1.dev1.dist-info/top_level.txt
msp360-0.0.1.dev1.dist-info/RECORD
